{
  "mode": "dry_run",
  "target_range": [
    401,
    500
  ],
  "target_count_existing": 53,
  "missing_ranks": [
    401,
    402,
    403,
    404,
    405,
    411,
    413,
    414,
    417,
    418,
    419,
    420,
    422,
    423,
    424,
    425,
    426,
    427,
    429,
    432,
    433,
    436,
    437,
    438,
    439,
    441,
    443,
    444,
    445,
    446,
    449,
    450,
    454,
    455,
    456,
    463,
    464,
    467,
    470,
    483,
    484,
    487,
    488,
    490,
    492,
    493,
    496
  ],
  "changed_count": 9,
  "residual_count": 0,
  "manual_hold_count": 12,
  "checked": [
    {
      "rank": 406,
      "fragment_id": "5cd36ee9-532d-4c25-848e-44e970918519",
      "source_ref": "mail_gold_v2_406_scn_2025",
      "scenario": "new_business_promotion",
      "old_title": "嘿，来和我们一起“视”界大冒险吧！",
      "new_title": "嘿，来和我们一起“视”界大冒险吧！",
      "changed": false,
      "residual_flags": [],
      "manual_hold_reasons": []
    },
    {
      "rank": 407,
      "fragment_id": "5b58cd88-2bbd-4d32-a1c3-b967e81ddaa9",
      "source_ref": "mail_gold_v2_407_scn_2025",
      "scenario": "new_business_promotion",
      "old_title": "活动搭建摄影直播同传和设备一体化服务-From [发件人] of Speed",
      "new_title": "活动搭建摄影直播同传和设备一体化服务-From [发件人] of Speed",
      "changed": false,
      "residual_flags": [],
      "manual_hold_reasons": []
    },
    {
      "rank": 408,
      "fragment_id": "fa613dd3-d5b3-4861-bf20-2d7998157092",
      "source_ref": "mail_gold_v2_408_scn_2025",
      "scenario": "new_business_promotion",
      "old_title": "机油单页印刷文件",
      "new_title": "机油单页印刷文件",
      "changed": false,
      "residual_flags": [],
      "manual_hold_reasons": [
        "cleaned_content_too_short"
      ]
    },
    {
      "rank": 409,
      "fragment_id": "163d6145-d316-430c-91ab-f7e7aed87877",
      "source_ref": "mail_gold_v2_409_scn_2025",
      "scenario": "new_business_promotion",
      "old_title": "进博会-同传译员book",
      "new_title": "进博会-同传译员book",
      "changed": false,
      "residual_flags": [],
      "manual_hold_reasons": [
        "cleaned_content_too_short"
      ]
    },
    {
      "rank": 410,
      "fragment_id": "e1a37fcc-b0d7-49c7-ad7a-f7b714e180f0",
      "source_ref": "mail_gold_v2_410_scn_2025",
      "scenario": "re_activation",
      "old_title": "继续为您提供多业务支持",
      "new_title": "继续为您提供多业务支持",
      "changed": false,
      "residual_flags": [],
      "manual_hold_reasons": []
    },
    {
      "rank": 412,
      "fragment_id": "f5363f15-ce88-41e7-b19e-20df9cdd6e72",
      "source_ref": "mail_gold_v2_412_scn_2025",
      "scenario": "new_contact_intro",
      "old_title": "来自SpeedAsia[发件人]的问候",
      "new_title": "来自SpeedAsia[发件人]的问候",
      "changed": true,
      "residual_flags": [],
      "manual_hold_reasons": [],
      "old_content": "范San，下午好\n\n我是SpeedAsia的销售经理[发件人]（[发件人]）\n\n很高兴有机会联系，承蒙关照，以下是我司简单介绍，请过目\n\nSpeedAsia创立于多年，主要为进驻中国的外企、各国领事馆提供专业的资料翻译、大型会议同声传译、样册的图文设计印刷、视频配音配字幕、活动展会搭建等专业服务\n\n迄今已连续多年获评先进企业，尤其在翻译行业，我们目前是上海规模最大、市场份额第1的专业公司\n\n以下是我司网站上最新的关于几项业务模块的视频介绍，欢迎随时点击浏览：\n\n视频主题短网址关键词\n\n非常希望接下来能有更多机会为贵公司提供服务，还请您多多关照",
      "new_content": "[客户称呼]，下午好\n\n我是SpeedAsia的销售经理[发件人]（[发件人]）\n\n很高兴有机会联系，承蒙关照，以下是我司简单介绍，请过目\n\nSpeedAsia创立于多年，主要为进驻中国的外企、各国领事馆提供专业的资料翻译、大型会议同声传译、样册的图文设计印刷、视频配音配字幕、活动展会搭建等专业服务\n\n迄今已尤其在翻译行业，我们目前是经验稳定的专业公司\n\n以下是我司网站上最新的关于几项业务模块的视频介绍，欢迎随时点击浏览：\n\n视频主题短网址关键词\n\n非常希望接下来能有更多机会为贵公司提供服务，还请您多多关照"
    },
    {
      "rank": 415,
      "fragment_id": "7f0e3a78-157a-4483-bca3-f705e50610c4",
      "source_ref": "mail_gold_v2_415_scn_2025",
      "scenario": "new_business_promotion",
      "old_title": "与您分享可参考的综合服务场景",
      "new_title": "与您分享可参考的综合服务场景",
      "changed": false,
      "residual_flags": [],
      "manual_hold_reasons": []
    },
    {
      "rank": 416,
      "fragment_id": "babcda08-097b-4ab2-9c04-cfe1a6e211cd",
      "source_ref": "mail_gold_v2_416_scn_2025",
      "scenario": "new_business_promotion",
      "old_title": "与您分享可参考的综合服务场景",
      "new_title": "与您分享可参考的综合服务场景",
      "changed": false,
      "residual_flags": [],
      "manual_hold_reasons": [
        "cleaned_content_too_short"
      ]
    },
    {
      "rank": 421,
      "fragment_id": "0a3667aa-dfb1-4873-9d37-30ba056b695b",
      "source_ref": "mail_gold_v2_421_scn_2025",
      "scenario": "new_business_promotion",
      "old_title": "同传老师Book-&2",
      "new_title": "同传老师Book-&2",
      "changed": false,
      "residual_flags": [],
      "manual_hold_reasons": []
    },
    {
      "rank": 428,
      "fragment_id": "d21fdc80-7a6e-4c63-8af0-6c2b4535f340",
      "source_ref": "mail_gold_v2_428_scn_2025",
      "scenario": "new_business_promotion",
      "old_title": "与您分享可参考的综合服务场景",
      "new_title": "与您分享可参考的综合服务场景",
      "changed": false,
      "residual_flags": [],
      "manual_hold_reasons": [
        "cleaned_content_too_short"
      ]
    },
    {
      "rank": 430,
      "fragment_id": "3c3a3af6-e42f-4f8c-9f82-43ed80ef41a1",
      "source_ref": "mail_gold_v2_430_scn_2025",
      "scenario": "new_business_promotion",
      "old_title": "AW: Chinese translation of SAN_TI_BCA141-01_EN_V01_San",
      "new_title": "AW: Chinese translation of SAN_TI_BCA141-01_EN_V01_San",
      "changed": false,
      "residual_flags": [],
      "manual_hold_reasons": []
    },
    {
      "rank": 431,
      "fragment_id": "d838497c-adb9-483d-aa02-73317a334655",
      "source_ref": "mail_gold_v2_431_scn_2025",
      "scenario": "new_business_promotion",
      "old_title": "与您分享可参考的综合服务场景",
      "new_title": "与您分享可参考的综合服务场景",
      "changed": false,
      "residual_flags": [],
      "manual_hold_reasons": [
        "cleaned_content_too_short"
      ]
    },
    {
      "rank": 434,
      "fragment_id": "6e8cfedd-5e62-40e4-9618-6925e22bb973",
      "source_ref": "mail_gold_v2_434_scn_2025",
      "scenario": "new_business_promotion",
      "old_title": "Print for HRC Handbook CN v19.4",
      "new_title": "Print for HRC Handbook CN v19.4",
      "changed": false,
      "residual_flags": [],
      "manual_hold_reasons": [
        "cleaned_content_too_short"
      ]
    },
    {
      "rank": 435,
      "fragment_id": "65746a10-6500-4125-b59e-06a9a8c27561",
      "source_ref": "mail_gold_v2_435_scn_2025",
      "scenario": "re_activation",
      "old_title": "继续为您提供多业务支持",
      "new_title": "继续为您提供多业务支持",
      "changed": true,
      "residual_flags": [],
      "manual_hold_reasons": [],
      "old_content": "[客户称呼]，下午好\n\nSpeedAsia信息科技发展有限公司，深耕行业多年，致力于为客户提供精准高效的语言解决方案\n\n为了让您更全面地了解我们的能力，我特意为您整理了核心业务介绍和部分精选案例：\n\nSpeedAsia核心优势与专注领域\n\n自多年扎根上海，我们已构建覆盖笔译、同传/交传口译、设计印刷、多媒体译制、展台/会议设计搭建的多元业务矩阵，始终坚持“专业深耕”，并连续多年获评“先进企业”\n\n近期精选案例：\n专业与效率的印证 (部分示例)\n\n生物制药： 1周内精准完成750分钟生物纯化技术视频的听写及字幕制作，确保术语精确与时间轴完美同步\n\n半导体： 为行业头部客户提供定期技术播客服务（每2周1期），系统匹配专业译员，保障听写、翻译、配音全流程技术表述精准\n\n美妆快消： 紧急响应某头部美妆品牌需求，下午3小时媒体访谈现场口译+跟录，次日上午即交付完整听写翻译稿，助力品牌快速传播\n\n我们能提供的多元服务：\n\n- 笔译服务：\n精准高效的语言解决方案\n\n- 同传口译：\n年均多领域会议经验，覆盖多语种\n\n- 多媒体译制：\n多语种覆盖，专业处理视频听写翻译、字幕制作及后期\n\n- 设计印刷：\n精研材质工艺，打造精准传达品牌调性的宣传物料\n\n- 展台/会议搭建：\n一站式服务，打造专业吸睛的品牌展示空间\n\n- 礼品定制：\n结合品牌文化，定制专属商务礼品方案\n\n附件中为您提供了更详细的翻译服务外的业务介绍，方便您随时查阅\n\n我非常珍视目前与某化工客户在翻译、设计排版及印刷业务上的良好合作！ 同时，我也热切期待能将这些专业能力延伸至更多领域——例如为贵司打造吸睛的展台、定制企业文化笔记本、台历等专属印刷品，礼品方案——全方位支持某化工客户的品牌建设与全球沟通\n\n若贵司对现有服务有深化需求，或希望探讨设计印刷、展台搭建等新合作方向，欢迎随时联系我\n\n再次感谢您的信任与时间\n\n期待与您有更多交流机会\n\n顺颂商祺\n\nSpeedAsia信息科技发展有限公司(SpeedAsia)",
      "new_content": "[客户称呼]，下午好\n\nSpeedAsia信息科技发展有限公司，深耕行业多年，致力于为客户提供精准高效的语言解决方案\n\n为了让您更全面地了解我们的能力，我特意为您整理了核心业务介绍和部分精选案例：\n\nSpeedAsia核心优势与专注领域\n\n自多年扎根上海，我们已构建覆盖笔译、同传/交传口译、设计印刷、多媒体译制、展台/会议设计搭建的多元业务矩阵，始终坚持“专业深耕”，并\n\n近期精选案例：\n专业与效率的印证 (部分示例)\n\n生物制药： 1周内精准完成750分钟生物纯化技术视频的听写及字幕制作，确保术语精确与时间轴完美同步\n\n半导体： 为行业头部客户提供定期技术播客服务（每2周1期），系统匹配专业译员，保障听写、翻译、配音全流程技术表述精准\n\n美妆快消： 紧急响应某头部美妆品牌需求，下午3小时媒体访谈现场口译+跟录，次日上午即交付完整听写翻译稿，助力品牌快速传播\n\n我们能提供的多元服务：\n\n- 笔译服务：\n精准高效的语言解决方案\n\n- 同传口译：\n年均多领域会议经验，覆盖多语种\n\n- 多媒体译制：\n多语种覆盖，专业处理视频听写翻译、字幕制作及后期\n\n- 设计印刷：\n精研材质工艺，打造精准传达品牌调性的宣传物料\n\n- 展台/会议搭建：\n一站式服务，打造专业吸睛的品牌展示空间\n\n- 礼品定制：\n结合品牌文化，定制专属商务礼品方案\n\n附件中为您提供了更详细的翻译服务外的业务介绍，方便您随时查阅\n\n我非常珍视目前与某化工客户在翻译、设计排版及印刷业务上的良好合作！ 同时，我也热切期待能将这些专业能力延伸至更多领域——例如为贵司打造吸睛的展台、定制企业文化笔记本、台历等专属印刷品，礼品方案——全方位支持某化工客户的品牌建设与全球沟通\n\n若贵司对现有服务有深化需求，或希望探讨设计印刷、展台搭建等新合作方向，欢迎随时联系我\n\n再次感谢您的信任与时间\n\n期待与您有更多交流机会\n\n顺颂商祺\n\nSpeedAsia信息科技发展有限公司(SpeedAsia)"
    },
    {
      "rank": 440,
      "fragment_id": "10e4d737-43cd-4924-b08c-ec315625281b",
      "source_ref": "mail_gold_v2_440_scn_2025",
      "scenario": "new_business_promotion",
      "old_title": "供您备查： SpeedAsia联系方式及业务概览存档",
      "new_title": "供您备查： SpeedAsia联系方式及业务概览存档",
      "changed": false,
      "residual_flags": [],
      "manual_hold_reasons": []
    },
    {
      "rank": 442,
      "fragment_id": "768fcf1b-9174-4553-b4b1-f1d2ab082cbe",
      "source_ref": "mail_gold_v2_442_scn_2025",
      "scenario": "new_business_promotion",
      "old_title": "合作邀请： 为西卡市场部提供本地化与市场活动支持",
      "new_title": "合作邀请： 为西卡市场部提供本地化与市场活动支持",
      "changed": false,
      "residual_flags": [],
      "manual_hold_reasons": []
    },
    {
      "rank": 447,
      "fragment_id": "d82d3dec-cd1d-4de2-b000-6bb5d2e0fc1d",
      "source_ref": "mail_gold_v2_447_scn_2025",
      "scenario": "new_contact_intro",
      "old_title": "上海嘉赛[发件人] - 很高兴今日与您通话，服务简介供参考",
      "new_title": "上海嘉赛[发件人] - 很高兴今日与您通话，服务简介供参考",
      "changed": false,
      "residual_flags": [],
      "manual_hold_reasons": []
    },
    {
      "rank": 448,
      "fragment_id": "f85787c2-831b-48ad-a72f-d5dbe712f5a6",
      "source_ref": "mail_gold_v2_448_scn_2025",
      "scenario": "new_business_promotion",
      "old_title": "与您分享可参考的综合服务场景",
      "new_title": "与您分享可参考的综合服务场景",
      "changed": true,
      "residual_flags": [],
      "manual_hold_reasons": [],
      "old_content": "Dear [客户称呼]\n\n衷心感谢您长期以来对我们翻译服务的信任与支持\n\n正是贵司的认可，让我们在深耕语言服务的道路上始终充满动力\n\n自多年扎根上海，SpeedAsia已专注语言解决方案多年\n\n我们从专业笔译出发，逐步延伸构建覆盖同传口译、多媒体译制、设计印刷、活动策划、展台搭建、礼品定制的六大业务矩阵，始终秉持“专业深耕”理念，连续多年获评行业“先进企业”\n\n我们的每一步拓展，都源于翻译业务的深厚积淀与技术延伸——\n\n▍精选翻译案例：\n专业与效率的印证\n\n生物制药：\n1周精准完成750分钟生物纯化技术视频听写及字幕制作，术语精准度达相应；\n\n半导体：\n为头部客户提供双周技术播客译制，系统性保障听写-翻译-配音全链路技术表述精准；\n\n美妆快消：\n紧急响应3小时媒体访谈同传+跟录，次日即交付完整译文，助力品牌全球传播\n\n▍延伸业务：\n一站式语言与品牌服务\n\n同传口译：\n年均服务500+场国际会议，覆盖多语种；\n\n多媒体译制：\n专业处理视频听写、多语字幕及后期制作；\n\n设计印刷：\n结合材质工艺创新，精准传递品牌调性；\n\n活动全案：\n依托多年跨文化经验，打造线上线下全流程活动；\n\n展台搭建：\n一站式品牌空间解决方案，提升海外参展影响力；\n\n礼品定制：\n深度融合品牌文化，定制高辨识度商务礼品\n\n附件为您奉上《公司介绍 MCom业务-V》，涵盖各领域服务细节与成功案例\n\n诚邀您将资料分享给相关团队，期待未来能继续深化合作，为贵司提供全面的语言与品牌服务支持\n\n再次感谢您的支持\n\n有任何需求，欢迎随时联系我",
      "new_content": "Dear [客户称呼]\n\n衷心感谢您长期以来对我们翻译服务的信任与支持\n\n正是贵司的认可，让我们在深耕语言服务的道路上始终充满动力\n\n自多年扎根上海，SpeedAsia已专注语言解决方案多年\n\n我们从专业笔译出发，逐步延伸构建覆盖同传口译、多媒体译制、设计印刷、活动策划、展台搭建、礼品定制的六大业务矩阵，始终秉持“专业深耕”理念\n\n我们的每一步拓展，都源于翻译业务的深厚积淀与技术延伸——\n\n▍精选翻译案例：\n专业与效率的印证\n\n生物制药：\n1周精准完成750分钟生物纯化技术视频听写及字幕制作，术语精准度达相应；\n\n半导体：\n为头部客户提供双周技术播客译制，系统性保障听写-翻译-配音全链路技术表述精准；\n\n美妆快消：\n紧急响应3小时媒体访谈同传+跟录，次日即交付完整译文，助力品牌全球传播\n\n▍延伸业务：\n一站式语言与品牌服务\n\n同传口译：\n年均服务500+场国际会议，覆盖多语种；\n\n多媒体译制：\n专业处理视频听写、多语字幕及后期制作；\n\n设计印刷：\n结合材质工艺创新，精准传递品牌调性；\n\n活动全案：\n依托多年跨文化经验，打造线上线下全流程活动；\n\n展台搭建：\n一站式品牌空间解决方案，提升海外参展影响力；\n\n礼品定制：\n深度融合品牌文化，定制高辨识度商务礼品\n\n附件为您奉上《公司介绍 MCom业务-V》，涵盖各领域服务细节与成功案例\n\n诚邀您将资料分享给相关团队，期待未来能继续深化合作，为贵司提供全面的语言与品牌服务支持\n\n再次感谢您的支持\n\n有任何需求，欢迎随时联系我"
    },
    {
      "rank": 451,
      "fragment_id": "b5538928-a925-4e12-9b01-ae7437f5eb4c",
      "source_ref": "mail_gold_v2_451_scn_2025",
      "scenario": "new_business_promotion",
      "old_title": "与您分享可参考的综合服务场景",
      "new_title": "与您分享可参考的综合服务场景",
      "changed": false,
      "residual_flags": [],
      "manual_hold_reasons": []
    },
    {
      "rank": 452,
      "fragment_id": "6ac4ec6a-e357-4d1f-b7eb-f8ee09fb0706",
      "source_ref": "mail_gold_v2_452_scn_2025",
      "scenario": "new_contact_intro",
      "old_title": "问候与更新——SpeedAsia期待继续为您服务",
      "new_title": "问候与更新——SpeedAsia期待继续为您服务",
      "changed": false,
      "residual_flags": [],
      "manual_hold_reasons": []
    },
    {
      "rank": 453,
      "fragment_id": "0ddec0b5-f440-4974-bfb7-3e510cc7e999",
      "source_ref": "mail_gold_v2_453_scn_2025",
      "scenario": "new_business_promotion",
      "old_title": "携手Syensqo｜来自某化工客户合作伙伴的一站式展台设计与展会服务方案",
      "new_title": "携手Syensqo｜来自某化工客户合作伙伴的一站式展台设计与展会服务方案",
      "changed": false,
      "residual_flags": [],
      "manual_hold_reasons": []
    },
    {
      "rank": 457,
      "fragment_id": "251dc169-c03a-438d-ad39-4b90729ba1fd",
      "source_ref": "mail_gold_v2_457_scn_2025",
      "scenario": "re_activation",
      "old_title": "继续为您提供多业务支持",
      "new_title": "继续为您提供多业务支持",
      "changed": true,
      "residual_flags": [],
      "manual_hold_reasons": [],
      "old_content": "Dear [客户称呼]\n\n在这的开端，首先\n\n愿如同晨曦中的第一缕阳光，为您带来新的希望与梦想的启航\n\n自多年成立以来，我们始终致力于语言服务与品牌传播领域，获得ISO认证后，已成为行业内的老牌综合性服务供应商，以专业技术和真诚服务赢得了客户的信赖\n\n二十多年来，我们有幸与众多企业携手合作，共同在全球舞台上创造了无数辉煌成就\n\n我们的核心业务包括：\n\n智能翻译：\n结合AI+ERP技术的创新应用，大幅提升工作效率相应，年处理字数超过相应\n\n高端口译：\n提供多语种语言组合的专业服务，无论线上线下均能无缝对接，每年支持会议\n\n创意设计与印刷：\n从样本设计到展台搭建，利用3D建模和虚拟现实技术为您的品牌增添独特魅力\n\n视频制作：\n采用AI语音识别、虚拟主播及智能剪辑等先进技术，引领数字化传播潮流\n\n商务礼品：\n通过智能推荐和个性化定制方案，让您的品牌更加深入人心\n\n展望我们期待继续与贵公司紧密合作，凭借我们服务多类型企业的丰富经验，为您提供更智能、高效的一站式解决方案\n\n是新的开始，也是追求梦想的新起点\n\n如果您有任何需求或想法，请随时联系我们\n\n让我们在这一年里共同创造更多精彩",
      "new_content": "Dear [客户称呼]\n\n在这的开端，首先\n\n愿如同晨曦中的第一缕阳光，为您带来新的希望与梦想的启航\n\n成立以来，我们始终致力于语言服务与品牌传播领域，获得ISO认证后，已成为行业内的老牌综合性服务供应商，以专业技术和真诚服务赢得了客户的信赖\n\n二十多年来，我们有幸与众多企业携手合作，共同在全球舞台上创造了无数辉煌成就\n\n我们的核心业务包括：\n\n智能翻译：\n结合AI+ERP技术的创新应用，大幅提升工作效率相应，年处理字数超过相应\n\n高端口译：\n提供多语种语言组合的专业服务，无论线上线下均能无缝对接，每年支持会议\n\n创意设计与印刷：\n从样本设计到展台搭建，利用3D建模和虚拟现实技术为您的品牌增添独特魅力\n\n视频制作：\n采用AI语音识别、虚拟主播及智能剪辑等先进技术，引领数字化传播潮流\n\n商务礼品：\n通过智能推荐和个性化定制方案，让您的品牌更加深入人心\n\n展望我们期待继续与贵公司紧密合作，凭借我们服务多类型企业的丰富经验，为您提供更智能、高效的一站式解决方案\n\n是新的开始，也是追求梦想的新起点\n\n如果您有任何需求或想法，请随时联系我们\n\n让我们在这一年里共同创造更多精彩"
    },
    {
      "rank": 458,
      "fragment_id": "103f8122-3e87-4644-9922-ff5411a7ca3b",
      "source_ref": "mail_gold_v2_458_scn_2025",
      "scenario": "re_activation",
      "old_title": "—— 用设计讲好品牌故事，值得信赖的定制伙伴",
      "new_title": "—— 用设计讲好品牌故事，值得信赖的定制伙伴",
      "changed": false,
      "residual_flags": [],
      "manual_hold_reasons": []
    },
    {
      "rank": 459,
      "fragment_id": "0e8dfe21-f1e6-4329-b94b-bdf69958dcc7",
      "source_ref": "mail_gold_v2_459_scn_2025",
      "scenario": "new_business_promotion",
      "old_title": "与您分享可参考的综合服务场景",
      "new_title": "与您分享可参考的综合服务场景",
      "changed": false,
      "residual_flags": [],
      "manual_hold_reasons": []
    },
    {
      "rank": 460,
      "fragment_id": "1657bf26-d963-4661-be71-0f3a13d850ab",
      "source_ref": "mail_gold_v2_460_scn_2025",
      "scenario": "new_business_promotion",
      "old_title": "与您分享可参考的综合服务场景",
      "new_title": "与您分享可参考的综合服务场景",
      "changed": false,
      "residual_flags": [],
      "manual_hold_reasons": []
    },
    {
      "rank": 461,
      "fragment_id": "fce16912-2d66-4460-aa23-0c060ba575e9",
      "source_ref": "mail_gold_v2_461_scn_2025",
      "scenario": "new_business_promotion",
      "old_title": "企业长期合作伙伴",
      "new_title": "企业长期合作伙伴",
      "changed": false,
      "residual_flags": [],
      "manual_hold_reasons": []
    },
    {
      "rank": 462,
      "fragment_id": "89df72f3-abf4-4af2-b19b-efe7a177fd05",
      "source_ref": "mail_gold_v2_462_scn_2025",
      "scenario": "new_business_promotion",
      "old_title": "770页手册更轻便？ 看我们如何实现“减重不减质”",
      "new_title": "770页手册更轻便？ 看我们如何实现“减重不减质”",
      "changed": false,
      "residual_flags": [],
      "manual_hold_reasons": []
    },
    {
      "rank": 465,
      "fragment_id": "64e500ff-5409-4d19-810a-80fc79cacbf0",
      "source_ref": "mail_gold_v2_465_scn_2025",
      "scenario": "new_contact_intro",
      "old_title": "Speed 一体化服务解决方案",
      "new_title": "Speed 一体化服务解决方案",
      "changed": false,
      "residual_flags": [],
      "manual_hold_reasons": []
    },
    {
      "rank": 466,
      "fragment_id": "9653bb6a-2fe1-4477-bb5e-1cad9fb9ab4f",
      "source_ref": "mail_gold_v2_466_scn_2025",
      "scenario": "new_contact_intro",
      "old_title": "Speed专业同传",
      "new_title": "Speed专业同传",
      "changed": true,
      "residual_flags": [],
      "manual_hold_reasons": [],
      "old_content": "Hi [客户称呼]\n\n我是SpeedAsia的[发件人]，很高兴刚才与您通话\n\n稍候我会给您同传会议方案，先简单给您做个介绍\n\n我们公司成立于多年，在翻译行业，我们目前是上海规模最大、市场份额第1的专业公司，我们为您同行业的斯派莎克、爱德华、泰科、沃茨、德来赛、斯必克、苏尔寿这些知名的企业合作很多年了，提供大量的技术翻译项目、各类会议口译和印刷项目\n\n在口译方面，我们拥有200余位通过欧盟或联合国等认证的同传人员，为高层次商业会谈,国际性会议，大型培训，国际会展等场合提供各类同传口译.\n\nSpeedAsia同传口译的特色:\n\n丰富的组织经验: 拥有成功组织各类国际性会议同声传译的丰富经验,保证选派最合适的并具备与会议主题相关的同传经验的口译人员\n\n训练有素的同传人员: 每名同传人员拥有至少近1000余次成功同传经验,能够做到准确,全面,同步的语言传递.\n\n充分的会前准备: 一旦接受客户委托,我们的同传人员将仔细研究会议的相关资料,做好充分的准备,以便在同声传译过程中迅速准确的进行同步翻译\n\n提供设备及人员一体化服务: 会议进行时，安排技术支持人员1-2名，随时提供跟进服务\n\n谢谢~~",
      "new_content": "Hi [客户称呼]\n\n我是SpeedAsia的[发件人]，很高兴刚才与您通话\n\n稍候我会给您同传会议方案，先简单给您做个介绍\n\n我们公司成立于多年，在翻译行业，我们目前是经验稳定的专业公司，我们为您同行业的斯派莎克、爱德华、泰科、沃茨、德来赛、斯必克、苏尔寿这些知名的企业合作很多年了，提供大量的技术翻译项目、各类会议口译和印刷项目\n\n在口译方面，我们拥有200余位通过欧盟或联合国等认证的同传人员，为高层次商业会谈,国际性会议，大型培训，国际会展等场合提供各类同传口译.\n\nSpeedAsia同传口译的特色:\n\n丰富的组织经验: 拥有成功组织各类国际性会议同声传译的丰富经验,保证选派最合适的并具备与会议主题相关的同传经验的口译人员\n\n训练有素的同传人员: 每名同传人员拥有至少近1000余次成功同传经验,能够做到准确,全面,同步的语言传递.\n\n充分的会前准备: 一旦接受客户委托,我们的同传人员将仔细研究会议的相关资料,做好充分的准备,以便在同声传译过程中迅速准确的进行同步翻译\n\n提供设备及人员一体化服务: 会议进行时，安排技术支持人员1-2名，随时提供跟进服务\n\n谢谢~~"
    },
    {
      "rank": 468,
      "fragment_id": "142ec855-9488-4e09-8ef0-9aed14bf9203",
      "source_ref": "mail_gold_v2_468_scn_2025",
      "scenario": "new_business_promotion",
      "old_title": "定制笔记本方案",
      "new_title": "定制笔记本方案",
      "changed": false,
      "residual_flags": [],
      "manual_hold_reasons": []
    },
    {
      "rank": 469,
      "fragment_id": "cbb5146f-4fea-42ea-bd46-b3a4cf5872e8",
      "source_ref": "mail_gold_v2_469_scn_2025",
      "scenario": "new_business_promotion",
      "old_title": "定制化解决方案+顶尖同传设备： 确保您的会议无后[客户称呼]之忧",
      "new_title": "定制化解决方案+顶尖同传设备： 确保您的会议无后[客户称呼]之忧",
      "changed": false,
      "residual_flags": [],
      "manual_hold_reasons": []
    },
    {
      "rank": 471,
      "fragment_id": "0b79c103-6b1a-4e29-aa99-c67970aa2a20",
      "source_ref": "mail_gold_v2_471_scn_2025",
      "scenario": "new_business_promotion",
      "old_title": "公司信息变更",
      "new_title": "公司信息变更",
      "changed": false,
      "residual_flags": [],
      "manual_hold_reasons": [
        "cleaned_content_too_short"
      ]
    },
    {
      "rank": 472,
      "fragment_id": "5fb350fe-e7c1-4549-af68-b482d5df7e89",
      "source_ref": "mail_gold_v2_472_scn_2025",
      "scenario": "new_business_promotion",
      "old_title": "关于技术文档翻译项目的跟进与服务支持",
      "new_title": "关于技术文档翻译项目的跟进与服务支持",
      "changed": false,
      "residual_flags": [],
      "manual_hold_reasons": []
    },
    {
      "rank": 473,
      "fragment_id": "d666767d-5306-433f-88f9-ce8e0f9f2386",
      "source_ref": "mail_gold_v2_473_scn_2025",
      "scenario": "new_business_promotion",
      "old_title": "关于罗马尼亚语翻译项目的跟进与服务支持",
      "new_title": "关于罗马尼亚语翻译项目的跟进与服务支持",
      "changed": false,
      "residual_flags": [],
      "manual_hold_reasons": []
    },
    {
      "rank": 474,
      "fragment_id": "c21c88d7-d187-44fa-93f4-0df2549edca1",
      "source_ref": "mail_gold_v2_474_scn_2025",
      "scenario": "new_business_promotion",
      "old_title": "关于拖链综合样本KABELSLEPP印刷前的最终确认",
      "new_title": "关于拖链综合样本KABELSLEPP印刷前的最终确认",
      "changed": false,
      "residual_flags": [],
      "manual_hold_reasons": []
    },
    {
      "rank": 475,
      "fragment_id": "6a45102d-bcc9-41fc-81a9-5d02e50be9dc",
      "source_ref": "mail_gold_v2_475_scn_2025",
      "scenario": "new_business_promotion",
      "old_title": "科勒展会翻译",
      "new_title": "科勒展会翻译",
      "changed": false,
      "residual_flags": [],
      "manual_hold_reasons": [
        "cleaned_content_too_short"
      ]
    },
    {
      "rank": 476,
      "fragment_id": "3d2333f5-8c7b-479d-b7f6-1c73094df62b",
      "source_ref": "mail_gold_v2_476_scn_2025",
      "scenario": "new_business_promotion",
      "old_title": "与您分享可参考的综合服务场景",
      "new_title": "与您分享可参考的综合服务场景",
      "changed": false,
      "residual_flags": [],
      "manual_hold_reasons": [
        "cleaned_content_too_short"
      ]
    },
    {
      "rank": 477,
      "fragment_id": "5e2a79de-720e-423f-be44-c5a6dcbf040f",
      "source_ref": "mail_gold_v2_477_scn_2025",
      "scenario": "new_business_promotion",
      "old_title": "与您分享可参考的综合服务场景",
      "new_title": "与您分享可参考的综合服务场景",
      "changed": false,
      "residual_flags": [],
      "manual_hold_reasons": [
        "cleaned_content_too_short"
      ]
    },
    {
      "rank": 478,
      "fragment_id": "80aaa315-8a68-487e-ac9f-273efacc7c3a",
      "source_ref": "mail_gold_v2_478_scn_2025",
      "scenario": "new_contact_intro",
      "old_title": "来自SpeedAsia的业务支持介绍",
      "new_title": "来自SpeedAsia的业务支持介绍",
      "changed": true,
      "residual_flags": [],
      "manual_hold_reasons": [],
      "old_content": "[客户称呼]，您好\n\n在刚刚结束的CPHI展会上，我们在拜访客户海发科技展台时，看到贵公司也参与了本次展会\n\n借此机会，我想向您介绍一下我们公司在医药领域所擅长的六大核心服务，希望能为贵公司在国际化发展过程中提供专业支持，也期待未来有机会与您建立深入的合作关系\n\n我们成立为多年，总部位于上海，拥有多年的行业经验\n\n作为业内少数实现全流程信息化管理的企业，我们自起便率先实施并持续迭代自主研发的ERP管理系统\n\n凭借多年的深耕发展，我们的核心团队成员均具备多年的专业背景，长期服务于某医药客户、某医药客户、某医药客户、某医药客户、某医药客户、某医疗器械客户等众多全球知名药企，为其在中国乃至亚太地区的市场拓展提供高效、精准的品牌传播支持\n\n我们的专业服务包括：\n\n智能翻译：\n通过ERP系统完美融合词库句库，大幅提升翻译效率与质量\n\n同传口译：\n每年为大小型商务会议及培训提供专业的同声传译服务\n\n设计印刷：\n从样本翻译到最终印刷品制作，再到展台搭建，为您提供一站式省时省心的服务体验\n\n视频制作：\n采用最新数字技术，让您的品牌传播更加生动有力\n\n商务礼品定制：\n个性化定制方案，赋予您的品牌更多温度与情感连接\n\n展台搭建：\n拥有丰富的展会设计与搭建经验，业务覆盖北上广深川渝等重要经济区域\n\n我们的核心优势包括：\n\n专业高效团队：\n核心成员从业超多年，具备国际视野与实战能力，可提供中英日德法等服务\n\n全流程服务：\n从翻译、设计、印刷到展台搭建，我们提供一站式整合服务，省时省心更省力\n\n技术驱动质量：\n率先实施ISO9001质量管理，并于引入ERP系统，融合术语库和句库，确保项目高效交付与统一品质\n\n创意与执行力并重：\n无论是会议口译、视频制作还是展台设计，我们都以创意助力品牌传播，以执行赢得客户信赖\n\n我非常期待有机会与贵公司建立合作，无论是翻译，同传/交传，制作印刷，还是在即将开展的国际会议、产品发布会，国内外展会，我们都愿成功您值得信赖的合作伙伴\n\n我们拥有众多成功的合作案例，展示了我们在多领域内的专业能力和创新解决方案\n\n期待与您进一步交流，共同探索合作的无限可能",
      "new_content": "[客户称呼]，您好\n\n在刚刚结束的CPHI展会上，我们在拜访客户某医药客户展台时，看到贵公司也参与了本次展会\n\n借此机会，我想向您介绍一下我们公司在医药领域所擅长的六大核心服务，希望能为贵公司在国际化发展过程中提供专业支持，也期待未来有机会与您建立深入的合作关系\n\n我们成立多年，总部位于上海，拥有多年的行业经验\n\n作为持续优化流程管理的服务团队，我们自起便率先实施并持续迭代自主研发的ERP管理系统\n\n凭借多年的深耕发展，我们的核心团队成员均具备多年的专业背景，长期服务于某医药客户、某医药客户、某医药客户、某医药客户、某医药客户、某医疗器械客户等众多全球知名药企，为其在中国乃至亚太地区的市场拓展提供高效、精准的品牌传播支持\n\n我们的专业服务包括：\n\n智能翻译：\n通过ERP系统完美融合词库句库，大幅提升翻译效率与质量\n\n同传口译：\n每年为大小型商务会议及培训提供专业的同声传译服务\n\n设计印刷：\n从样本翻译到最终印刷品制作，再到展台搭建，为您提供一站式省时省心的服务体验\n\n视频制作：\n采用最新数字技术，让您的品牌传播更加生动有力\n\n商务礼品定制：\n个性化定制方案，赋予您的品牌更多温度与情感连接\n\n展台搭建：\n拥有丰富的展会设计与搭建经验，业务覆盖北上广深川渝等重要经济区域\n\n我们的核心优势包括：\n\n专业高效团队：\n核心成员从业超多年，具备国际视野与实战能力，可提供中英日德法等服务\n\n全流程服务：\n从翻译、设计、印刷到展台搭建，我们提供一站式整合服务，省时省心更省力\n\n技术驱动质量：\n率先实施ISO9001质量管理，并于引入ERP系统，融合术语库和句库，确保项目高效交付与统一品质\n\n创意与执行力并重：\n无论是会议口译、视频制作还是展台设计，我们都以创意助力品牌传播，以执行赢得客户信赖\n\n我非常期待有机会与贵公司建立合作，无论是翻译，同传/交传，制作印刷，还是在即将开展的国际会议、产品发布会，国内外展会，我们都愿成功您值得信赖的合作伙伴\n\n我们拥有众多成功的合作案例，展示了我们在多领域内的专业能力和创新解决方案\n\n期待与您进一步交流，共同探索合作的无限可能"
    },
    {
      "rank": 479,
      "fragment_id": "70da80b7-6a3a-4fc0-92c2-bb45160e8007",
      "source_ref": "mail_gold_v2_479_scn_2025",
      "scenario": "new_business_promotion",
      "old_title": "岁月印记，台历中的商业智慧",
      "new_title": "岁月印记，台历中的商业智慧",
      "changed": false,
      "residual_flags": [],
      "manual_hold_reasons": []
    },
    {
      "rank": 480,
      "fragment_id": "62b2d3a5-ee9c-4f3c-b0f0-5d047377f13c",
      "source_ref": "mail_gold_v2_480_scn_2025",
      "scenario": "re_activation",
      "old_title": "通过高品质服务，我们成为众多外企的首选合作伙伴",
      "new_title": "通过高品质服务，我们成为众多外企的首选合作伙伴",
      "changed": true,
      "residual_flags": [],
      "manual_hold_reasons": [],
      "old_content": "随着MSC地中海奢华邮轮在亚太区业务的蓬勃扩展，我们非常荣幸成为其值得信赖的服务提供商\n\n客户选择我们，不仅因为我们在业界的良好声誉得到了众多外企客户的推荐，更因为我们拥有多年的丰富行业经验，能够提供从多语种翻译、精美印刷到引人注目的展示设计等一体化服务\n\n我们的核心团队成员均拥有超过多年的从业经验，长期为包括某工业客户、L'Oréal、某医药客户、某化工客户、Invista、HSBC、Alstom、某工业客户、Mitsubishi、Yamaha等在内的众多世界企业提供高品质、高效率的品牌传播与市场推广解决方案\n\n挑战\n\n翻译精准且富为期有吸引力：\n需要将各类个月手册翻译成简体中文、事实繁体中文及英文版本，上前不仅要求语言转换准确年年无误，还需具备卓越的底节语言功底，确保内容生庆活动吸引目标受众\n\n动便符合区域语言习惯：\n繁已开体中文版，不仅要考虑始直从简体到繁体的转换，持续更要贴合香港、台湾地到月区独特的语言文化习惯底冰\n\n色彩统一与一致雪活性：\n为了在同一展示区动结内同时陈列英文版、简束为体中文版和繁体中文版止期手册，必须保证所有版间包本的颜色严格一致，避含了免任何视觉差异\n\n高端大气的设计风格：\n易拉宝作为品牌形象的元宵重要组成部分，需体现节滑MSC地中海邮轮的品牌奢华感，提升品牌的雪节国际形象\n\n耐用性四个和稳定性：\n考虑到展会重要和门店的实际使用环境的节，易拉宝需要具备高质庆活量标准，既不易损坏也动可具有良好的稳定性，确谓节保在各种场合下都能完中有美展现\n\n我们的解决方案门每\n\n深厚行业背届冬景：\n自多年成立以来，凭令哈借多年的丰富经验，我们已成尔滨为世界企业的首选合作街道伙伴，以专业和广场高效著称\n\n张灯全方位一站式服结彩务：\n作为一体化男女综合性服务供应老幼商，我们提供从喜气精准翻译、创意洋洋设计、高品质印冰雪刷到安全高效的艺术搭建服务，满足冰雪企业市场推广的体育所有需求\n\n冰雪专业翻译团队：\n饮食拥有精通多语言冰雪的专业翻译团队经贸，能够深入理解冰雪不同地区的语言旅游文化特点，确保冰雪翻译后的文本既会展能传达原意又能等各引起共鸣\n\n项活顶尖印刷技术：\n动在采用德国进口的银白先进印刷设备，的世确保无论哪种语界里言版本的手册，有声在色彩和质量上有色都达到极致统一地开\n\n创新设计展起：\n由资深设计师来中团队操刀，我们国北为众多外企客户方名量身打造了包括城霎样本、海报、易大范拉宝、展台及活围高动视觉在内的多气压元化创意作品，反气广受客户好评\n\n选择我们，意味着节节选择了品质与信任中套\n\n我们将继续秉持节喜专业精神，助力每上加一位客户在全球市喜多场上取得更大成功喜盈",
      "new_content": "随着某文旅客户在亚太区业务的蓬勃扩展，我们非常荣幸成为其值得信赖的服务提供商\n\n客户选择我们，不仅因为我们在业界的良好声誉得到了众多外企客户的推荐，更因为我们拥有多年的丰富行业经验，能够提供从多语种翻译、精美印刷到引人注目的展示设计等一体化服务\n\n我们的核心团队成员均拥有超过多年的从业经验，长期为包括某工业客户、某消费品客户、某医药客户、某化工客户、某材料客户、某金融客户、某工业客户、某工业客户、某制造业客户、某制造业客户等在内的众多世界企业提供高品质、高效率的品牌传播与市场推广解决方案\n\n挑战\n\n翻译精准且富为期有吸引力：\n需要将各类个月手册翻译成简体中文、事实繁体中文及英文版本，上前不仅要求语言转换准确年年无误，还需具备卓越的底节语言功底，确保内容生庆活动吸引目标受众\n\n动便符合区域语言习惯：\n繁已开体中文版，不仅要考虑始直从简体到繁体的转换，持续更要贴合香港、台湾地到月区独特的语言文化习惯底冰\n\n色彩统一与一致雪活性：\n为了在同一展示区动结内同时陈列英文版、简束为体中文版和繁体中文版止期手册，必须保证所有版间包本的颜色严格一致，避含了免任何视觉差异\n\n高端大气的设计风格：\n易拉宝作为品牌形象的元宵重要组成部分，需体现节滑MSC地中海邮轮的品牌奢华感，提升品牌的雪节国际形象\n\n耐用性四个和稳定性：\n考虑到展会重要和门店的实际使用环境的节，易拉宝需要具备高质庆活量标准，既不易损坏也动可具有良好的稳定性，确谓节保在各种场合下都能完中有美展现\n\n我们的解决方案门每\n\n深厚行业背届冬景：\n成立以来，凭令哈借多年的丰富经验，我们已成尔滨为世界企业的首选合作街道伙伴，以专业和广场高效著称\n\n张灯全方位一站式服结彩务：\n作为一体化男女综合性服务供应老幼商，我们提供从喜气精准翻译、创意洋洋设计、高品质印冰雪刷到安全高效的艺术搭建服务，满足冰雪企业市场推广的体育所有需求\n\n冰雪专业翻译团队：\n饮食拥有精通多语言冰雪的专业翻译团队经贸，能够深入理解冰雪不同地区的语言旅游文化特点，确保冰雪翻译后的文本既会展能传达原意又能等各引起共鸣\n\n项活顶尖印刷技术：\n动在采用德国进口的银白先进印刷设备，的世确保无论哪种语界里言版本的手册，有声在色彩和质量上有色都达到极致统一地开\n\n创新设计展起：\n由资深设计师来中团队操刀，我们国北为众多外企客户方名量身打造了包括城霎样本、海报、易大范拉宝、展台及活围高动视觉在内的多气压元化创意作品，反气广受客户好评\n\n选择我们，意味着节节选择了品质与信任中套\n\n我们将继续秉持节喜专业精神，助力每上加一位客户在全球市喜多场上取得更大成功喜盈"
    },
    {
      "rank": 481,
      "fragment_id": "cc381bf4-1dcf-4f2f-bef3-8284fd2f1b5a",
      "source_ref": "mail_gold_v2_481_scn_2025",
      "scenario": "new_business_promotion",
      "old_title": "同传案例",
      "new_title": "同传案例",
      "changed": false,
      "residual_flags": [],
      "manual_hold_reasons": []
    },
    {
      "rank": 482,
      "fragment_id": "ca2429b3-25b9-46ed-a884-7e4be5e772d5",
      "source_ref": "mail_gold_v2_482_scn_2025",
      "scenario": "new_business_promotion",
      "old_title": "外企的选择不只看价格，更看重我们的专业与效率",
      "new_title": "外企的选择不只看价格，更看重我们的专业与效率",
      "changed": true,
      "residual_flags": [],
      "manual_hold_reasons": [],
      "old_content": "在当前充满挑战的市场环境中，参加行业展会仍是拓展业务、接触潜在客户的重要方式\n\n然而，在预算受限的情况下，如何既节省成本又能吸引观众目光，成为关键\n\n一套兼[客户称呼]成本控制与展可以示效果的专业参展解决影响方案：\n\n独树一帜的设全国计：\n通过整体协调的设它南计方案，将您的核心产下时品置于视觉焦点，迅速受影吸引参观者注意，提升响大品牌识别度\n\n经济实的是用挂画制作：\n采用便捷渤海挂钩设计，支持多种尺黄海寸选择，便于安装、拆其次卸与重复使用，大幅降是东低参展成本，同时实现海和完美展示效果\n\n我们拥有多年的深厚行业经验湿度，能够提供涵盖都上多语言翻译、高升锋品质印刷及引人后受注目的展示设计冷空在内的一站式综气团合服务\n\n我们的控制核心团队成员均气温具备超过多年的专业背景，长急降期为包括某工业客户、L'Oréal、某医药客户、某医药客户、ExxonMobil、某化工客户、某医疗器械客户、Coca-Cola、HSBC、Alstom、某工业客户、Mitsubishi和Yamaha在内的多家世界湿度企业提供高效、优质的变小品牌传播与市场冬季推广解决方案，的强建立了稳定而深冷风入的合作关系\n\n无论您是9平方的标准展台，还是200平方的特装展台，我到整们都能提供从设计到个南执行的一站式参展服海如务，确保您参展无忧果冷：\n\n展台设计与搭建空气：\n从创意构思到现场移动搭建，打造独特、引缓慢人注目的展示空间，高压助您在众多展商中脱前缘颖而出\n\n印刷解决就是方案：\n包括宣传手册型冷、易拉宝等各类平面锋空物料的高质量印刷，气它精准呈现品牌形象\n\n来临\n\n视频本地化服务：\n时出将宣传视频翻译并制现层作成多语种版本，帮状云助跨越语言障碍，扩系和大影响力\n\n现场口连续译支持：\n专业口译团性降队提供交替传译或同水气声传译服务，保障展压风会期间沟通顺畅\n\n温度文档翻译服务：\n提供和湿准确、专业的商务及度的技术文档翻译，确保变化信息传递无误\n\n让我们携手合作，南海以创新设计和高效很强服务，为您量身定的冷制最适合的参展方空气案，助您在有限预可以算下实现最大参展影响价值\n\nSpeedAsiaSpeedAsia",
      "new_content": "在当前充满挑战的市场环境中，参加行业展会仍是拓展业务、接触潜在客户的重要方式\n\n然而，在预算受限的情况下，如何既节省成本又能吸引观众目光，成为关键\n\n一套兼[客户称呼]成本控制与展可以示效果的专业参展解决影响方案：\n\n独树一帜的设全国计：\n通过整体协调的设它南计方案，将您的核心产下时品置于视觉焦点，迅速受影吸引参观者注意，提升响大品牌识别度\n\n经济实的是用挂画制作：\n采用便捷渤海挂钩设计，支持多种尺黄海寸选择，便于安装、拆其次卸与重复使用，大幅降是东低参展成本，同时实现海和完美展示效果\n\n我们拥有多年的深厚行业经验湿度，能够提供涵盖都上多语言翻译、高升锋品质印刷及引人后受注目的展示设计冷空在内的一站式综气团合服务\n\n我们的控制核心团队成员均气温具备超过多年的专业背景，长急降期为包括某工业客户、某消费品客户、某医药客户、某医药客户、ExxonMobil、某化工客户、某医疗器械客户、Coca-Cola、某金融客户、某工业客户、某工业客户、某制造业客户和某制造业客户在内的多家世界湿度企业提供高效、优质的变小品牌传播与市场冬季推广解决方案，的强建立了稳定而深冷风入的合作关系\n\n无论您是9平方的标准展台，还是200平方的特装展台，我到整们都能提供从设计到个南执行的一站式参展服海如务，确保您参展无忧果冷：\n\n展台设计与搭建空气：\n从创意构思到现场移动搭建，打造独特、引缓慢人注目的展示空间，高压助您在众多展商中脱前缘颖而出\n\n印刷解决就是方案：\n包括宣传手册型冷、易拉宝等各类平面锋空物料的高质量印刷，气它精准呈现品牌形象\n\n来临\n\n视频本地化服务：\n时出将宣传视频翻译并制现层作成多语种版本，帮状云助跨越语言障碍，扩系和大影响力\n\n现场口连续译支持：\n专业口译团性降队提供交替传译或同水气声传译服务，保障展压风会期间沟通顺畅\n\n温度文档翻译服务：\n提供和湿准确、专业的商务及度的技术文档翻译，确保变化信息传递无误\n\n让我们携手合作，南海以创新设计和高效很强服务，为您量身定的冷制最适合的参展方空气案，助您在有限预可以算下实现最大参展影响价值\n\nSpeedAsiaSpeedAsia"
    },
    {
      "rank": 485,
      "fragment_id": "e1666afa-92b9-42bb-a7b0-321eafa2e44c",
      "source_ref": "mail_gold_v2_485_scn_2025",
      "scenario": "new_business_promotion",
      "old_title": "小空间，大效果——专业活动策划案例分享",
      "new_title": "小空间，大效果——专业活动策划案例分享",
      "changed": false,
      "residual_flags": [],
      "manual_hold_reasons": []
    },
    {
      "rank": 486,
      "fragment_id": "c45b3cc7-e404-467a-b763-af7c5ae1b13e",
      "source_ref": "mail_gold_v2_486_scn_2025",
      "scenario": "new_business_promotion",
      "old_title": "一站式活动解决方案",
      "new_title": "一站式活动解决方案",
      "changed": false,
      "residual_flags": [],
      "manual_hold_reasons": []
    },
    {
      "rank": 489,
      "fragment_id": "9725ae9c-8d50-491f-81e1-62f8aadc28df",
      "source_ref": "mail_gold_v2_489_scn_2025",
      "scenario": "new_business_promotion",
      "old_title": "与您分享可参考的综合服务场景",
      "new_title": "与您分享可参考的综合服务场景",
      "changed": false,
      "residual_flags": [],
      "manual_hold_reasons": []
    },
    {
      "rank": 491,
      "fragment_id": "21a5033f-2028-4872-b570-e2ce180108ad",
      "source_ref": "mail_gold_v2_491_scn_2025",
      "scenario": "new_contact_intro",
      "old_title": "电话没有联系上您，我是SpeedAsia市场部的[发件人],关于视频制作招投标项目与您确认下",
      "new_title": "电话没有联系上您，我是SpeedAsia市场部的[发件人],关于视频制作招投标项目与您确认下",
      "changed": false,
      "residual_flags": [],
      "manual_hold_reasons": [
        "cleaned_content_too_short"
      ]
    },
    {
      "rank": 494,
      "fragment_id": "a96036a5-a830-4653-88f4-dda4e8d9fff3",
      "source_ref": "mail_gold_v2_494_scn_2024",
      "scenario": "new_contact_intro",
      "old_title": "某化工客户---SpeedAsia合作",
      "new_title": "某化工客户---SpeedAsia合作",
      "changed": false,
      "residual_flags": [],
      "manual_hold_reasons": [
        "cleaned_content_too_short"
      ]
    },
    {
      "rank": 495,
      "fragment_id": "4dfeb93d-ced9-4fb1-9997-0905e368257d",
      "source_ref": "mail_gold_v2_495_scn_2024",
      "scenario": "new_contact_intro",
      "old_title": "SpeedAsia业务交接",
      "new_title": "SpeedAsia业务交接",
      "changed": false,
      "residual_flags": [],
      "manual_hold_reasons": []
    },
    {
      "rank": 497,
      "fragment_id": "9c4cbe96-1069-454d-8288-30572981e72e",
      "source_ref": "mail_gold_v2_497_scn_2024",
      "scenario": "new_contact_intro",
      "old_title": "谢谢您的电话沟通，我是交大SpeedAsia公司的[发件人]，劳驾发送下入库资料",
      "new_title": "谢谢您的电话沟通，我是交大SpeedAsia公司的[发件人]，劳驾发送下入库资料",
      "changed": true,
      "residual_flags": [],
      "manual_hold_reasons": [],
      "old_content": "广西电力供应链，您好\n\n我们与贵司已合作很多年了，劳驾您将入库资料发送于我，我在这两天填好回传于您~\n\n我们交大SpeedAsia创立于多年，至今已多年了，主要为进驻中国的外企、各国领事馆提供专业的资料翻译、大型会议同声传译、样册的图文设计印刷、视频译制等专业服务\n\n迄今已连续多年获评先进企业尤其在翻译行业，我们目前是上海规模最大、市场份额第1的专业公司\n\n公司在业内率先实施ISO9001质量标准、并于全面实施了ERP数据库管理系统\n\n我们自主研发的业内最领先的互联网翻译平台，连通客户和译员，确保高效运营各类口笔译项目\n\n经过20余年的数据积累，我们拥有了业内最强大的行业翻译句对和词汇数据库，有力保证了翻译质量的稳定，这对许多跨国公司，是非常重要的\n\n若您有相关需求，欢迎随时与我联系，也拜托您将我们推荐给您的同事\n\n关于我们\n\n华东地区规模领先的翻译、印刷、多媒体译制一体化服务供应商\n\n多年+行业经验，多语种、100+行业、相应条专业句对\n\n世界的首选印刷供应商，累计印刷量达到五百多万册\n\n提供业内顶级的交替传译同声传译服务，主要服务于各种高端会议场合",
      "new_content": "贵司，您好\n\n我们与贵司已合作很多年了，劳驾您将入库资料发送于我，我在这两天填好回传于您~\n\n我们交大SpeedAsia创立于多年，至今已多年了，主要为进驻中国的外企、各国领事馆提供专业的资料翻译、大型会议同声传译、样册的图文设计印刷、视频译制等专业服务\n\n迄今已我们目前是经验稳定的专业公司\n\n公司在业内率先实施ISO9001质量标准、并于全面实施了ERP数据库管理系统\n\n我们自主研发的成熟的行业项目管理能力，连通客户和译员，确保高效运营各类口笔译项目\n\n经过20余年的数据积累，我们拥有了成熟的行业项目管理能力，有力保证了翻译质量的稳定，这对许多跨国公司，是非常重要的\n\n若您有相关需求，欢迎随时与我联系，也拜托您将我们推荐给您的同事\n\n关于我们\n\n华东地区规模领先的翻译、印刷、多媒体译制一体化服务供应商\n\n多年+行业经验，多语种、100+行业、相应条专业句对\n\n世界的首选印刷供应商，累计印刷量达到五百多万册\n\n提供业内顶级的交替传译同声传译服务，主要服务于各种高端会议场合"
    },
    {
      "rank": 498,
      "fragment_id": "4fb5e116-2e8a-4f3c-a921-4d574976b3ec",
      "source_ref": "mail_gold_v2_498_scn_2024",
      "scenario": "new_business_promotion",
      "old_title": "关于通讯行业我们的成功案例，请查阅",
      "new_title": "关于通讯行业我们的成功案例，请查阅",
      "changed": false,
      "residual_flags": [],
      "manual_hold_reasons": []
    },
    {
      "rank": 499,
      "fragment_id": "26072b68-4fc9-40e9-aae1-628af6e0771f",
      "source_ref": "mail_gold_v2_499_scn_2024",
      "scenario": "new_contact_intro",
      "old_title": "强生---SpeedAsia业务介绍",
      "new_title": "强生---SpeedAsia业务介绍",
      "changed": false,
      "residual_flags": [],
      "manual_hold_reasons": []
    },
    {
      "rank": 500,
      "fragment_id": "de8dbbf0-7120-4815-9c38-0aad8173bc4a",
      "source_ref": "mail_gold_v2_500_scn_2024",
      "scenario": "new_business_promotion",
      "old_title": "SpeedAsia 同传案例分享",
      "new_title": "SpeedAsia 同传案例分享",
      "changed": false,
      "residual_flags": [],
      "manual_hold_reasons": []
    }
  ],
  "changed": [
    {
      "rank": 412,
      "fragment_id": "f5363f15-ce88-41e7-b19e-20df9cdd6e72",
      "source_ref": "mail_gold_v2_412_scn_2025",
      "scenario": "new_contact_intro",
      "old_title": "来自SpeedAsia[发件人]的问候",
      "new_title": "来自SpeedAsia[发件人]的问候",
      "changed": true,
      "residual_flags": [],
      "manual_hold_reasons": [],
      "old_content": "范San，下午好\n\n我是SpeedAsia的销售经理[发件人]（[发件人]）\n\n很高兴有机会联系，承蒙关照，以下是我司简单介绍，请过目\n\nSpeedAsia创立于多年，主要为进驻中国的外企、各国领事馆提供专业的资料翻译、大型会议同声传译、样册的图文设计印刷、视频配音配字幕、活动展会搭建等专业服务\n\n迄今已连续多年获评先进企业，尤其在翻译行业，我们目前是上海规模最大、市场份额第1的专业公司\n\n以下是我司网站上最新的关于几项业务模块的视频介绍，欢迎随时点击浏览：\n\n视频主题短网址关键词\n\n非常希望接下来能有更多机会为贵公司提供服务，还请您多多关照",
      "new_content": "[客户称呼]，下午好\n\n我是SpeedAsia的销售经理[发件人]（[发件人]）\n\n很高兴有机会联系，承蒙关照，以下是我司简单介绍，请过目\n\nSpeedAsia创立于多年，主要为进驻中国的外企、各国领事馆提供专业的资料翻译、大型会议同声传译、样册的图文设计印刷、视频配音配字幕、活动展会搭建等专业服务\n\n迄今已尤其在翻译行业，我们目前是经验稳定的专业公司\n\n以下是我司网站上最新的关于几项业务模块的视频介绍，欢迎随时点击浏览：\n\n视频主题短网址关键词\n\n非常希望接下来能有更多机会为贵公司提供服务，还请您多多关照"
    },
    {
      "rank": 435,
      "fragment_id": "65746a10-6500-4125-b59e-06a9a8c27561",
      "source_ref": "mail_gold_v2_435_scn_2025",
      "scenario": "re_activation",
      "old_title": "继续为您提供多业务支持",
      "new_title": "继续为您提供多业务支持",
      "changed": true,
      "residual_flags": [],
      "manual_hold_reasons": [],
      "old_content": "[客户称呼]，下午好\n\nSpeedAsia信息科技发展有限公司，深耕行业多年，致力于为客户提供精准高效的语言解决方案\n\n为了让您更全面地了解我们的能力，我特意为您整理了核心业务介绍和部分精选案例：\n\nSpeedAsia核心优势与专注领域\n\n自多年扎根上海，我们已构建覆盖笔译、同传/交传口译、设计印刷、多媒体译制、展台/会议设计搭建的多元业务矩阵，始终坚持“专业深耕”，并连续多年获评“先进企业”\n\n近期精选案例：\n专业与效率的印证 (部分示例)\n\n生物制药： 1周内精准完成750分钟生物纯化技术视频的听写及字幕制作，确保术语精确与时间轴完美同步\n\n半导体： 为行业头部客户提供定期技术播客服务（每2周1期），系统匹配专业译员，保障听写、翻译、配音全流程技术表述精准\n\n美妆快消： 紧急响应某头部美妆品牌需求，下午3小时媒体访谈现场口译+跟录，次日上午即交付完整听写翻译稿，助力品牌快速传播\n\n我们能提供的多元服务：\n\n- 笔译服务：\n精准高效的语言解决方案\n\n- 同传口译：\n年均多领域会议经验，覆盖多语种\n\n- 多媒体译制：\n多语种覆盖，专业处理视频听写翻译、字幕制作及后期\n\n- 设计印刷：\n精研材质工艺，打造精准传达品牌调性的宣传物料\n\n- 展台/会议搭建：\n一站式服务，打造专业吸睛的品牌展示空间\n\n- 礼品定制：\n结合品牌文化，定制专属商务礼品方案\n\n附件中为您提供了更详细的翻译服务外的业务介绍，方便您随时查阅\n\n我非常珍视目前与某化工客户在翻译、设计排版及印刷业务上的良好合作！ 同时，我也热切期待能将这些专业能力延伸至更多领域——例如为贵司打造吸睛的展台、定制企业文化笔记本、台历等专属印刷品，礼品方案——全方位支持某化工客户的品牌建设与全球沟通\n\n若贵司对现有服务有深化需求，或希望探讨设计印刷、展台搭建等新合作方向，欢迎随时联系我\n\n再次感谢您的信任与时间\n\n期待与您有更多交流机会\n\n顺颂商祺\n\nSpeedAsia信息科技发展有限公司(SpeedAsia)",
      "new_content": "[客户称呼]，下午好\n\nSpeedAsia信息科技发展有限公司，深耕行业多年，致力于为客户提供精准高效的语言解决方案\n\n为了让您更全面地了解我们的能力，我特意为您整理了核心业务介绍和部分精选案例：\n\nSpeedAsia核心优势与专注领域\n\n自多年扎根上海，我们已构建覆盖笔译、同传/交传口译、设计印刷、多媒体译制、展台/会议设计搭建的多元业务矩阵，始终坚持“专业深耕”，并\n\n近期精选案例：\n专业与效率的印证 (部分示例)\n\n生物制药： 1周内精准完成750分钟生物纯化技术视频的听写及字幕制作，确保术语精确与时间轴完美同步\n\n半导体： 为行业头部客户提供定期技术播客服务（每2周1期），系统匹配专业译员，保障听写、翻译、配音全流程技术表述精准\n\n美妆快消： 紧急响应某头部美妆品牌需求，下午3小时媒体访谈现场口译+跟录，次日上午即交付完整听写翻译稿，助力品牌快速传播\n\n我们能提供的多元服务：\n\n- 笔译服务：\n精准高效的语言解决方案\n\n- 同传口译：\n年均多领域会议经验，覆盖多语种\n\n- 多媒体译制：\n多语种覆盖，专业处理视频听写翻译、字幕制作及后期\n\n- 设计印刷：\n精研材质工艺，打造精准传达品牌调性的宣传物料\n\n- 展台/会议搭建：\n一站式服务，打造专业吸睛的品牌展示空间\n\n- 礼品定制：\n结合品牌文化，定制专属商务礼品方案\n\n附件中为您提供了更详细的翻译服务外的业务介绍，方便您随时查阅\n\n我非常珍视目前与某化工客户在翻译、设计排版及印刷业务上的良好合作！ 同时，我也热切期待能将这些专业能力延伸至更多领域——例如为贵司打造吸睛的展台、定制企业文化笔记本、台历等专属印刷品，礼品方案——全方位支持某化工客户的品牌建设与全球沟通\n\n若贵司对现有服务有深化需求，或希望探讨设计印刷、展台搭建等新合作方向，欢迎随时联系我\n\n再次感谢您的信任与时间\n\n期待与您有更多交流机会\n\n顺颂商祺\n\nSpeedAsia信息科技发展有限公司(SpeedAsia)"
    },
    {
      "rank": 448,
      "fragment_id": "f85787c2-831b-48ad-a72f-d5dbe712f5a6",
      "source_ref": "mail_gold_v2_448_scn_2025",
      "scenario": "new_business_promotion",
      "old_title": "与您分享可参考的综合服务场景",
      "new_title": "与您分享可参考的综合服务场景",
      "changed": true,
      "residual_flags": [],
      "manual_hold_reasons": [],
      "old_content": "Dear [客户称呼]\n\n衷心感谢您长期以来对我们翻译服务的信任与支持\n\n正是贵司的认可，让我们在深耕语言服务的道路上始终充满动力\n\n自多年扎根上海，SpeedAsia已专注语言解决方案多年\n\n我们从专业笔译出发，逐步延伸构建覆盖同传口译、多媒体译制、设计印刷、活动策划、展台搭建、礼品定制的六大业务矩阵，始终秉持“专业深耕”理念，连续多年获评行业“先进企业”\n\n我们的每一步拓展，都源于翻译业务的深厚积淀与技术延伸——\n\n▍精选翻译案例：\n专业与效率的印证\n\n生物制药：\n1周精准完成750分钟生物纯化技术视频听写及字幕制作，术语精准度达相应；\n\n半导体：\n为头部客户提供双周技术播客译制，系统性保障听写-翻译-配音全链路技术表述精准；\n\n美妆快消：\n紧急响应3小时媒体访谈同传+跟录，次日即交付完整译文，助力品牌全球传播\n\n▍延伸业务：\n一站式语言与品牌服务\n\n同传口译：\n年均服务500+场国际会议，覆盖多语种；\n\n多媒体译制：\n专业处理视频听写、多语字幕及后期制作；\n\n设计印刷：\n结合材质工艺创新，精准传递品牌调性；\n\n活动全案：\n依托多年跨文化经验，打造线上线下全流程活动；\n\n展台搭建：\n一站式品牌空间解决方案，提升海外参展影响力；\n\n礼品定制：\n深度融合品牌文化，定制高辨识度商务礼品\n\n附件为您奉上《公司介绍 MCom业务-V》，涵盖各领域服务细节与成功案例\n\n诚邀您将资料分享给相关团队，期待未来能继续深化合作，为贵司提供全面的语言与品牌服务支持\n\n再次感谢您的支持\n\n有任何需求，欢迎随时联系我",
      "new_content": "Dear [客户称呼]\n\n衷心感谢您长期以来对我们翻译服务的信任与支持\n\n正是贵司的认可，让我们在深耕语言服务的道路上始终充满动力\n\n自多年扎根上海，SpeedAsia已专注语言解决方案多年\n\n我们从专业笔译出发，逐步延伸构建覆盖同传口译、多媒体译制、设计印刷、活动策划、展台搭建、礼品定制的六大业务矩阵，始终秉持“专业深耕”理念\n\n我们的每一步拓展，都源于翻译业务的深厚积淀与技术延伸——\n\n▍精选翻译案例：\n专业与效率的印证\n\n生物制药：\n1周精准完成750分钟生物纯化技术视频听写及字幕制作，术语精准度达相应；\n\n半导体：\n为头部客户提供双周技术播客译制，系统性保障听写-翻译-配音全链路技术表述精准；\n\n美妆快消：\n紧急响应3小时媒体访谈同传+跟录，次日即交付完整译文，助力品牌全球传播\n\n▍延伸业务：\n一站式语言与品牌服务\n\n同传口译：\n年均服务500+场国际会议，覆盖多语种；\n\n多媒体译制：\n专业处理视频听写、多语字幕及后期制作；\n\n设计印刷：\n结合材质工艺创新，精准传递品牌调性；\n\n活动全案：\n依托多年跨文化经验，打造线上线下全流程活动；\n\n展台搭建：\n一站式品牌空间解决方案，提升海外参展影响力；\n\n礼品定制：\n深度融合品牌文化，定制高辨识度商务礼品\n\n附件为您奉上《公司介绍 MCom业务-V》，涵盖各领域服务细节与成功案例\n\n诚邀您将资料分享给相关团队，期待未来能继续深化合作，为贵司提供全面的语言与品牌服务支持\n\n再次感谢您的支持\n\n有任何需求，欢迎随时联系我"
    },
    {
      "rank": 457,
      "fragment_id": "251dc169-c03a-438d-ad39-4b90729ba1fd",
      "source_ref": "mail_gold_v2_457_scn_2025",
      "scenario": "re_activation",
      "old_title": "继续为您提供多业务支持",
      "new_title": "继续为您提供多业务支持",
      "changed": true,
      "residual_flags": [],
      "manual_hold_reasons": [],
      "old_content": "Dear [客户称呼]\n\n在这的开端，首先\n\n愿如同晨曦中的第一缕阳光，为您带来新的希望与梦想的启航\n\n自多年成立以来，我们始终致力于语言服务与品牌传播领域，获得ISO认证后，已成为行业内的老牌综合性服务供应商，以专业技术和真诚服务赢得了客户的信赖\n\n二十多年来，我们有幸与众多企业携手合作，共同在全球舞台上创造了无数辉煌成就\n\n我们的核心业务包括：\n\n智能翻译：\n结合AI+ERP技术的创新应用，大幅提升工作效率相应，年处理字数超过相应\n\n高端口译：\n提供多语种语言组合的专业服务，无论线上线下均能无缝对接，每年支持会议\n\n创意设计与印刷：\n从样本设计到展台搭建，利用3D建模和虚拟现实技术为您的品牌增添独特魅力\n\n视频制作：\n采用AI语音识别、虚拟主播及智能剪辑等先进技术，引领数字化传播潮流\n\n商务礼品：\n通过智能推荐和个性化定制方案，让您的品牌更加深入人心\n\n展望我们期待继续与贵公司紧密合作，凭借我们服务多类型企业的丰富经验，为您提供更智能、高效的一站式解决方案\n\n是新的开始，也是追求梦想的新起点\n\n如果您有任何需求或想法，请随时联系我们\n\n让我们在这一年里共同创造更多精彩",
      "new_content": "Dear [客户称呼]\n\n在这的开端，首先\n\n愿如同晨曦中的第一缕阳光，为您带来新的希望与梦想的启航\n\n成立以来，我们始终致力于语言服务与品牌传播领域，获得ISO认证后，已成为行业内的老牌综合性服务供应商，以专业技术和真诚服务赢得了客户的信赖\n\n二十多年来，我们有幸与众多企业携手合作，共同在全球舞台上创造了无数辉煌成就\n\n我们的核心业务包括：\n\n智能翻译：\n结合AI+ERP技术的创新应用，大幅提升工作效率相应，年处理字数超过相应\n\n高端口译：\n提供多语种语言组合的专业服务，无论线上线下均能无缝对接，每年支持会议\n\n创意设计与印刷：\n从样本设计到展台搭建，利用3D建模和虚拟现实技术为您的品牌增添独特魅力\n\n视频制作：\n采用AI语音识别、虚拟主播及智能剪辑等先进技术，引领数字化传播潮流\n\n商务礼品：\n通过智能推荐和个性化定制方案，让您的品牌更加深入人心\n\n展望我们期待继续与贵公司紧密合作，凭借我们服务多类型企业的丰富经验，为您提供更智能、高效的一站式解决方案\n\n是新的开始，也是追求梦想的新起点\n\n如果您有任何需求或想法，请随时联系我们\n\n让我们在这一年里共同创造更多精彩"
    },
    {
      "rank": 466,
      "fragment_id": "9653bb6a-2fe1-4477-bb5e-1cad9fb9ab4f",
      "source_ref": "mail_gold_v2_466_scn_2025",
      "scenario": "new_contact_intro",
      "old_title": "Speed专业同传",
      "new_title": "Speed专业同传",
      "changed": true,
      "residual_flags": [],
      "manual_hold_reasons": [],
      "old_content": "Hi [客户称呼]\n\n我是SpeedAsia的[发件人]，很高兴刚才与您通话\n\n稍候我会给您同传会议方案，先简单给您做个介绍\n\n我们公司成立于多年，在翻译行业，我们目前是上海规模最大、市场份额第1的专业公司，我们为您同行业的斯派莎克、爱德华、泰科、沃茨、德来赛、斯必克、苏尔寿这些知名的企业合作很多年了，提供大量的技术翻译项目、各类会议口译和印刷项目\n\n在口译方面，我们拥有200余位通过欧盟或联合国等认证的同传人员，为高层次商业会谈,国际性会议，大型培训，国际会展等场合提供各类同传口译.\n\nSpeedAsia同传口译的特色:\n\n丰富的组织经验: 拥有成功组织各类国际性会议同声传译的丰富经验,保证选派最合适的并具备与会议主题相关的同传经验的口译人员\n\n训练有素的同传人员: 每名同传人员拥有至少近1000余次成功同传经验,能够做到准确,全面,同步的语言传递.\n\n充分的会前准备: 一旦接受客户委托,我们的同传人员将仔细研究会议的相关资料,做好充分的准备,以便在同声传译过程中迅速准确的进行同步翻译\n\n提供设备及人员一体化服务: 会议进行时，安排技术支持人员1-2名，随时提供跟进服务\n\n谢谢~~",
      "new_content": "Hi [客户称呼]\n\n我是SpeedAsia的[发件人]，很高兴刚才与您通话\n\n稍候我会给您同传会议方案，先简单给您做个介绍\n\n我们公司成立于多年，在翻译行业，我们目前是经验稳定的专业公司，我们为您同行业的斯派莎克、爱德华、泰科、沃茨、德来赛、斯必克、苏尔寿这些知名的企业合作很多年了，提供大量的技术翻译项目、各类会议口译和印刷项目\n\n在口译方面，我们拥有200余位通过欧盟或联合国等认证的同传人员，为高层次商业会谈,国际性会议，大型培训，国际会展等场合提供各类同传口译.\n\nSpeedAsia同传口译的特色:\n\n丰富的组织经验: 拥有成功组织各类国际性会议同声传译的丰富经验,保证选派最合适的并具备与会议主题相关的同传经验的口译人员\n\n训练有素的同传人员: 每名同传人员拥有至少近1000余次成功同传经验,能够做到准确,全面,同步的语言传递.\n\n充分的会前准备: 一旦接受客户委托,我们的同传人员将仔细研究会议的相关资料,做好充分的准备,以便在同声传译过程中迅速准确的进行同步翻译\n\n提供设备及人员一体化服务: 会议进行时，安排技术支持人员1-2名，随时提供跟进服务\n\n谢谢~~"
    },
    {
      "rank": 478,
      "fragment_id": "80aaa315-8a68-487e-ac9f-273efacc7c3a",
      "source_ref": "mail_gold_v2_478_scn_2025",
      "scenario": "new_contact_intro",
      "old_title": "来自SpeedAsia的业务支持介绍",
      "new_title": "来自SpeedAsia的业务支持介绍",
      "changed": true,
      "residual_flags": [],
      "manual_hold_reasons": [],
      "old_content": "[客户称呼]，您好\n\n在刚刚结束的CPHI展会上，我们在拜访客户海发科技展台时，看到贵公司也参与了本次展会\n\n借此机会，我想向您介绍一下我们公司在医药领域所擅长的六大核心服务，希望能为贵公司在国际化发展过程中提供专业支持，也期待未来有机会与您建立深入的合作关系\n\n我们成立为多年，总部位于上海，拥有多年的行业经验\n\n作为业内少数实现全流程信息化管理的企业，我们自起便率先实施并持续迭代自主研发的ERP管理系统\n\n凭借多年的深耕发展，我们的核心团队成员均具备多年的专业背景，长期服务于某医药客户、某医药客户、某医药客户、某医药客户、某医药客户、某医疗器械客户等众多全球知名药企，为其在中国乃至亚太地区的市场拓展提供高效、精准的品牌传播支持\n\n我们的专业服务包括：\n\n智能翻译：\n通过ERP系统完美融合词库句库，大幅提升翻译效率与质量\n\n同传口译：\n每年为大小型商务会议及培训提供专业的同声传译服务\n\n设计印刷：\n从样本翻译到最终印刷品制作，再到展台搭建，为您提供一站式省时省心的服务体验\n\n视频制作：\n采用最新数字技术，让您的品牌传播更加生动有力\n\n商务礼品定制：\n个性化定制方案，赋予您的品牌更多温度与情感连接\n\n展台搭建：\n拥有丰富的展会设计与搭建经验，业务覆盖北上广深川渝等重要经济区域\n\n我们的核心优势包括：\n\n专业高效团队：\n核心成员从业超多年，具备国际视野与实战能力，可提供中英日德法等服务\n\n全流程服务：\n从翻译、设计、印刷到展台搭建，我们提供一站式整合服务，省时省心更省力\n\n技术驱动质量：\n率先实施ISO9001质量管理，并于引入ERP系统，融合术语库和句库，确保项目高效交付与统一品质\n\n创意与执行力并重：\n无论是会议口译、视频制作还是展台设计，我们都以创意助力品牌传播，以执行赢得客户信赖\n\n我非常期待有机会与贵公司建立合作，无论是翻译，同传/交传，制作印刷，还是在即将开展的国际会议、产品发布会，国内外展会，我们都愿成功您值得信赖的合作伙伴\n\n我们拥有众多成功的合作案例，展示了我们在多领域内的专业能力和创新解决方案\n\n期待与您进一步交流，共同探索合作的无限可能",
      "new_content": "[客户称呼]，您好\n\n在刚刚结束的CPHI展会上，我们在拜访客户某医药客户展台时，看到贵公司也参与了本次展会\n\n借此机会，我想向您介绍一下我们公司在医药领域所擅长的六大核心服务，希望能为贵公司在国际化发展过程中提供专业支持，也期待未来有机会与您建立深入的合作关系\n\n我们成立多年，总部位于上海，拥有多年的行业经验\n\n作为持续优化流程管理的服务团队，我们自起便率先实施并持续迭代自主研发的ERP管理系统\n\n凭借多年的深耕发展，我们的核心团队成员均具备多年的专业背景，长期服务于某医药客户、某医药客户、某医药客户、某医药客户、某医药客户、某医疗器械客户等众多全球知名药企，为其在中国乃至亚太地区的市场拓展提供高效、精准的品牌传播支持\n\n我们的专业服务包括：\n\n智能翻译：\n通过ERP系统完美融合词库句库，大幅提升翻译效率与质量\n\n同传口译：\n每年为大小型商务会议及培训提供专业的同声传译服务\n\n设计印刷：\n从样本翻译到最终印刷品制作，再到展台搭建，为您提供一站式省时省心的服务体验\n\n视频制作：\n采用最新数字技术，让您的品牌传播更加生动有力\n\n商务礼品定制：\n个性化定制方案，赋予您的品牌更多温度与情感连接\n\n展台搭建：\n拥有丰富的展会设计与搭建经验，业务覆盖北上广深川渝等重要经济区域\n\n我们的核心优势包括：\n\n专业高效团队：\n核心成员从业超多年，具备国际视野与实战能力，可提供中英日德法等服务\n\n全流程服务：\n从翻译、设计、印刷到展台搭建，我们提供一站式整合服务，省时省心更省力\n\n技术驱动质量：\n率先实施ISO9001质量管理，并于引入ERP系统，融合术语库和句库，确保项目高效交付与统一品质\n\n创意与执行力并重：\n无论是会议口译、视频制作还是展台设计，我们都以创意助力品牌传播，以执行赢得客户信赖\n\n我非常期待有机会与贵公司建立合作，无论是翻译，同传/交传，制作印刷，还是在即将开展的国际会议、产品发布会，国内外展会，我们都愿成功您值得信赖的合作伙伴\n\n我们拥有众多成功的合作案例，展示了我们在多领域内的专业能力和创新解决方案\n\n期待与您进一步交流，共同探索合作的无限可能"
    },
    {
      "rank": 480,
      "fragment_id": "62b2d3a5-ee9c-4f3c-b0f0-5d047377f13c",
      "source_ref": "mail_gold_v2_480_scn_2025",
      "scenario": "re_activation",
      "old_title": "通过高品质服务，我们成为众多外企的首选合作伙伴",
      "new_title": "通过高品质服务，我们成为众多外企的首选合作伙伴",
      "changed": true,
      "residual_flags": [],
      "manual_hold_reasons": [],
      "old_content": "随着MSC地中海奢华邮轮在亚太区业务的蓬勃扩展，我们非常荣幸成为其值得信赖的服务提供商\n\n客户选择我们，不仅因为我们在业界的良好声誉得到了众多外企客户的推荐，更因为我们拥有多年的丰富行业经验，能够提供从多语种翻译、精美印刷到引人注目的展示设计等一体化服务\n\n我们的核心团队成员均拥有超过多年的从业经验，长期为包括某工业客户、L'Oréal、某医药客户、某化工客户、Invista、HSBC、Alstom、某工业客户、Mitsubishi、Yamaha等在内的众多世界企业提供高品质、高效率的品牌传播与市场推广解决方案\n\n挑战\n\n翻译精准且富为期有吸引力：\n需要将各类个月手册翻译成简体中文、事实繁体中文及英文版本，上前不仅要求语言转换准确年年无误，还需具备卓越的底节语言功底，确保内容生庆活动吸引目标受众\n\n动便符合区域语言习惯：\n繁已开体中文版，不仅要考虑始直从简体到繁体的转换，持续更要贴合香港、台湾地到月区独特的语言文化习惯底冰\n\n色彩统一与一致雪活性：\n为了在同一展示区动结内同时陈列英文版、简束为体中文版和繁体中文版止期手册，必须保证所有版间包本的颜色严格一致，避含了免任何视觉差异\n\n高端大气的设计风格：\n易拉宝作为品牌形象的元宵重要组成部分，需体现节滑MSC地中海邮轮的品牌奢华感，提升品牌的雪节国际形象\n\n耐用性四个和稳定性：\n考虑到展会重要和门店的实际使用环境的节，易拉宝需要具备高质庆活量标准，既不易损坏也动可具有良好的稳定性，确谓节保在各种场合下都能完中有美展现\n\n我们的解决方案门每\n\n深厚行业背届冬景：\n自多年成立以来，凭令哈借多年的丰富经验，我们已成尔滨为世界企业的首选合作街道伙伴，以专业和广场高效著称\n\n张灯全方位一站式服结彩务：\n作为一体化男女综合性服务供应老幼商，我们提供从喜气精准翻译、创意洋洋设计、高品质印冰雪刷到安全高效的艺术搭建服务，满足冰雪企业市场推广的体育所有需求\n\n冰雪专业翻译团队：\n饮食拥有精通多语言冰雪的专业翻译团队经贸，能够深入理解冰雪不同地区的语言旅游文化特点，确保冰雪翻译后的文本既会展能传达原意又能等各引起共鸣\n\n项活顶尖印刷技术：\n动在采用德国进口的银白先进印刷设备，的世确保无论哪种语界里言版本的手册，有声在色彩和质量上有色都达到极致统一地开\n\n创新设计展起：\n由资深设计师来中团队操刀，我们国北为众多外企客户方名量身打造了包括城霎样本、海报、易大范拉宝、展台及活围高动视觉在内的多气压元化创意作品，反气广受客户好评\n\n选择我们，意味着节节选择了品质与信任中套\n\n我们将继续秉持节喜专业精神，助力每上加一位客户在全球市喜多场上取得更大成功喜盈",
      "new_content": "随着某文旅客户在亚太区业务的蓬勃扩展，我们非常荣幸成为其值得信赖的服务提供商\n\n客户选择我们，不仅因为我们在业界的良好声誉得到了众多外企客户的推荐，更因为我们拥有多年的丰富行业经验，能够提供从多语种翻译、精美印刷到引人注目的展示设计等一体化服务\n\n我们的核心团队成员均拥有超过多年的从业经验，长期为包括某工业客户、某消费品客户、某医药客户、某化工客户、某材料客户、某金融客户、某工业客户、某工业客户、某制造业客户、某制造业客户等在内的众多世界企业提供高品质、高效率的品牌传播与市场推广解决方案\n\n挑战\n\n翻译精准且富为期有吸引力：\n需要将各类个月手册翻译成简体中文、事实繁体中文及英文版本，上前不仅要求语言转换准确年年无误，还需具备卓越的底节语言功底，确保内容生庆活动吸引目标受众\n\n动便符合区域语言习惯：\n繁已开体中文版，不仅要考虑始直从简体到繁体的转换，持续更要贴合香港、台湾地到月区独特的语言文化习惯底冰\n\n色彩统一与一致雪活性：\n为了在同一展示区动结内同时陈列英文版、简束为体中文版和繁体中文版止期手册，必须保证所有版间包本的颜色严格一致，避含了免任何视觉差异\n\n高端大气的设计风格：\n易拉宝作为品牌形象的元宵重要组成部分，需体现节滑MSC地中海邮轮的品牌奢华感，提升品牌的雪节国际形象\n\n耐用性四个和稳定性：\n考虑到展会重要和门店的实际使用环境的节，易拉宝需要具备高质庆活量标准，既不易损坏也动可具有良好的稳定性，确谓节保在各种场合下都能完中有美展现\n\n我们的解决方案门每\n\n深厚行业背届冬景：\n成立以来，凭令哈借多年的丰富经验，我们已成尔滨为世界企业的首选合作街道伙伴，以专业和广场高效著称\n\n张灯全方位一站式服结彩务：\n作为一体化男女综合性服务供应老幼商，我们提供从喜气精准翻译、创意洋洋设计、高品质印冰雪刷到安全高效的艺术搭建服务，满足冰雪企业市场推广的体育所有需求\n\n冰雪专业翻译团队：\n饮食拥有精通多语言冰雪的专业翻译团队经贸，能够深入理解冰雪不同地区的语言旅游文化特点，确保冰雪翻译后的文本既会展能传达原意又能等各引起共鸣\n\n项活顶尖印刷技术：\n动在采用德国进口的银白先进印刷设备，的世确保无论哪种语界里言版本的手册，有声在色彩和质量上有色都达到极致统一地开\n\n创新设计展起：\n由资深设计师来中团队操刀，我们国北为众多外企客户方名量身打造了包括城霎样本、海报、易大范拉宝、展台及活围高动视觉在内的多气压元化创意作品，反气广受客户好评\n\n选择我们，意味着节节选择了品质与信任中套\n\n我们将继续秉持节喜专业精神，助力每上加一位客户在全球市喜多场上取得更大成功喜盈"
    },
    {
      "rank": 482,
      "fragment_id": "ca2429b3-25b9-46ed-a884-7e4be5e772d5",
      "source_ref": "mail_gold_v2_482_scn_2025",
      "scenario": "new_business_promotion",
      "old_title": "外企的选择不只看价格，更看重我们的专业与效率",
      "new_title": "外企的选择不只看价格，更看重我们的专业与效率",
      "changed": true,
      "residual_flags": [],
      "manual_hold_reasons": [],
      "old_content": "在当前充满挑战的市场环境中，参加行业展会仍是拓展业务、接触潜在客户的重要方式\n\n然而，在预算受限的情况下，如何既节省成本又能吸引观众目光，成为关键\n\n一套兼[客户称呼]成本控制与展可以示效果的专业参展解决影响方案：\n\n独树一帜的设全国计：\n通过整体协调的设它南计方案，将您的核心产下时品置于视觉焦点，迅速受影吸引参观者注意，提升响大品牌识别度\n\n经济实的是用挂画制作：\n采用便捷渤海挂钩设计，支持多种尺黄海寸选择，便于安装、拆其次卸与重复使用，大幅降是东低参展成本，同时实现海和完美展示效果\n\n我们拥有多年的深厚行业经验湿度，能够提供涵盖都上多语言翻译、高升锋品质印刷及引人后受注目的展示设计冷空在内的一站式综气团合服务\n\n我们的控制核心团队成员均气温具备超过多年的专业背景，长急降期为包括某工业客户、L'Oréal、某医药客户、某医药客户、ExxonMobil、某化工客户、某医疗器械客户、Coca-Cola、HSBC、Alstom、某工业客户、Mitsubishi和Yamaha在内的多家世界湿度企业提供高效、优质的变小品牌传播与市场冬季推广解决方案，的强建立了稳定而深冷风入的合作关系\n\n无论您是9平方的标准展台，还是200平方的特装展台，我到整们都能提供从设计到个南执行的一站式参展服海如务，确保您参展无忧果冷：\n\n展台设计与搭建空气：\n从创意构思到现场移动搭建，打造独特、引缓慢人注目的展示空间，高压助您在众多展商中脱前缘颖而出\n\n印刷解决就是方案：\n包括宣传手册型冷、易拉宝等各类平面锋空物料的高质量印刷，气它精准呈现品牌形象\n\n来临\n\n视频本地化服务：\n时出将宣传视频翻译并制现层作成多语种版本，帮状云助跨越语言障碍，扩系和大影响力\n\n现场口连续译支持：\n专业口译团性降队提供交替传译或同水气声传译服务，保障展压风会期间沟通顺畅\n\n温度文档翻译服务：\n提供和湿准确、专业的商务及度的技术文档翻译，确保变化信息传递无误\n\n让我们携手合作，南海以创新设计和高效很强服务，为您量身定的冷制最适合的参展方空气案，助您在有限预可以算下实现最大参展影响价值\n\nSpeedAsiaSpeedAsia",
      "new_content": "在当前充满挑战的市场环境中，参加行业展会仍是拓展业务、接触潜在客户的重要方式\n\n然而，在预算受限的情况下，如何既节省成本又能吸引观众目光，成为关键\n\n一套兼[客户称呼]成本控制与展可以示效果的专业参展解决影响方案：\n\n独树一帜的设全国计：\n通过整体协调的设它南计方案，将您的核心产下时品置于视觉焦点，迅速受影吸引参观者注意，提升响大品牌识别度\n\n经济实的是用挂画制作：\n采用便捷渤海挂钩设计，支持多种尺黄海寸选择，便于安装、拆其次卸与重复使用，大幅降是东低参展成本，同时实现海和完美展示效果\n\n我们拥有多年的深厚行业经验湿度，能够提供涵盖都上多语言翻译、高升锋品质印刷及引人后受注目的展示设计冷空在内的一站式综气团合服务\n\n我们的控制核心团队成员均气温具备超过多年的专业背景，长急降期为包括某工业客户、某消费品客户、某医药客户、某医药客户、ExxonMobil、某化工客户、某医疗器械客户、Coca-Cola、某金融客户、某工业客户、某工业客户、某制造业客户和某制造业客户在内的多家世界湿度企业提供高效、优质的变小品牌传播与市场冬季推广解决方案，的强建立了稳定而深冷风入的合作关系\n\n无论您是9平方的标准展台，还是200平方的特装展台，我到整们都能提供从设计到个南执行的一站式参展服海如务，确保您参展无忧果冷：\n\n展台设计与搭建空气：\n从创意构思到现场移动搭建，打造独特、引缓慢人注目的展示空间，高压助您在众多展商中脱前缘颖而出\n\n印刷解决就是方案：\n包括宣传手册型冷、易拉宝等各类平面锋空物料的高质量印刷，气它精准呈现品牌形象\n\n来临\n\n视频本地化服务：\n时出将宣传视频翻译并制现层作成多语种版本，帮状云助跨越语言障碍，扩系和大影响力\n\n现场口连续译支持：\n专业口译团性降队提供交替传译或同水气声传译服务，保障展压风会期间沟通顺畅\n\n温度文档翻译服务：\n提供和湿准确、专业的商务及度的技术文档翻译，确保变化信息传递无误\n\n让我们携手合作，南海以创新设计和高效很强服务，为您量身定的冷制最适合的参展方空气案，助您在有限预可以算下实现最大参展影响价值\n\nSpeedAsiaSpeedAsia"
    },
    {
      "rank": 497,
      "fragment_id": "9c4cbe96-1069-454d-8288-30572981e72e",
      "source_ref": "mail_gold_v2_497_scn_2024",
      "scenario": "new_contact_intro",
      "old_title": "谢谢您的电话沟通，我是交大SpeedAsia公司的[发件人]，劳驾发送下入库资料",
      "new_title": "谢谢您的电话沟通，我是交大SpeedAsia公司的[发件人]，劳驾发送下入库资料",
      "changed": true,
      "residual_flags": [],
      "manual_hold_reasons": [],
      "old_content": "广西电力供应链，您好\n\n我们与贵司已合作很多年了，劳驾您将入库资料发送于我，我在这两天填好回传于您~\n\n我们交大SpeedAsia创立于多年，至今已多年了，主要为进驻中国的外企、各国领事馆提供专业的资料翻译、大型会议同声传译、样册的图文设计印刷、视频译制等专业服务\n\n迄今已连续多年获评先进企业尤其在翻译行业，我们目前是上海规模最大、市场份额第1的专业公司\n\n公司在业内率先实施ISO9001质量标准、并于全面实施了ERP数据库管理系统\n\n我们自主研发的业内最领先的互联网翻译平台，连通客户和译员，确保高效运营各类口笔译项目\n\n经过20余年的数据积累，我们拥有了业内最强大的行业翻译句对和词汇数据库，有力保证了翻译质量的稳定，这对许多跨国公司，是非常重要的\n\n若您有相关需求，欢迎随时与我联系，也拜托您将我们推荐给您的同事\n\n关于我们\n\n华东地区规模领先的翻译、印刷、多媒体译制一体化服务供应商\n\n多年+行业经验，多语种、100+行业、相应条专业句对\n\n世界的首选印刷供应商，累计印刷量达到五百多万册\n\n提供业内顶级的交替传译同声传译服务，主要服务于各种高端会议场合",
      "new_content": "贵司，您好\n\n我们与贵司已合作很多年了，劳驾您将入库资料发送于我，我在这两天填好回传于您~\n\n我们交大SpeedAsia创立于多年，至今已多年了，主要为进驻中国的外企、各国领事馆提供专业的资料翻译、大型会议同声传译、样册的图文设计印刷、视频译制等专业服务\n\n迄今已我们目前是经验稳定的专业公司\n\n公司在业内率先实施ISO9001质量标准、并于全面实施了ERP数据库管理系统\n\n我们自主研发的成熟的行业项目管理能力，连通客户和译员，确保高效运营各类口笔译项目\n\n经过20余年的数据积累，我们拥有了成熟的行业项目管理能力，有力保证了翻译质量的稳定，这对许多跨国公司，是非常重要的\n\n若您有相关需求，欢迎随时与我联系，也拜托您将我们推荐给您的同事\n\n关于我们\n\n华东地区规模领先的翻译、印刷、多媒体译制一体化服务供应商\n\n多年+行业经验，多语种、100+行业、相应条专业句对\n\n世界的首选印刷供应商，累计印刷量达到五百多万册\n\n提供业内顶级的交替传译同声传译服务，主要服务于各种高端会议场合"
    }
  ],
  "residual": [],
  "manual_hold": [
    {
      "rank": 408,
      "fragment_id": "fa613dd3-d5b3-4861-bf20-2d7998157092",
      "source_ref": "mail_gold_v2_408_scn_2025",
      "title": "机油单页印刷文件",
      "reasons": [
        "cleaned_content_too_short"
      ]
    },
    {
      "rank": 409,
      "fragment_id": "163d6145-d316-430c-91ab-f7e7aed87877",
      "source_ref": "mail_gold_v2_409_scn_2025",
      "title": "进博会-同传译员book",
      "reasons": [
        "cleaned_content_too_short"
      ]
    },
    {
      "rank": 416,
      "fragment_id": "babcda08-097b-4ab2-9c04-cfe1a6e211cd",
      "source_ref": "mail_gold_v2_416_scn_2025",
      "title": "与您分享可参考的综合服务场景",
      "reasons": [
        "cleaned_content_too_short"
      ]
    },
    {
      "rank": 428,
      "fragment_id": "d21fdc80-7a6e-4c63-8af0-6c2b4535f340",
      "source_ref": "mail_gold_v2_428_scn_2025",
      "title": "与您分享可参考的综合服务场景",
      "reasons": [
        "cleaned_content_too_short"
      ]
    },
    {
      "rank": 431,
      "fragment_id": "d838497c-adb9-483d-aa02-73317a334655",
      "source_ref": "mail_gold_v2_431_scn_2025",
      "title": "与您分享可参考的综合服务场景",
      "reasons": [
        "cleaned_content_too_short"
      ]
    },
    {
      "rank": 434,
      "fragment_id": "6e8cfedd-5e62-40e4-9618-6925e22bb973",
      "source_ref": "mail_gold_v2_434_scn_2025",
      "title": "Print for HRC Handbook CN v19.4",
      "reasons": [
        "cleaned_content_too_short"
      ]
    },
    {
      "rank": 471,
      "fragment_id": "0b79c103-6b1a-4e29-aa99-c67970aa2a20",
      "source_ref": "mail_gold_v2_471_scn_2025",
      "title": "公司信息变更",
      "reasons": [
        "cleaned_content_too_short"
      ]
    },
    {
      "rank": 475,
      "fragment_id": "6a45102d-bcc9-41fc-81a9-5d02e50be9dc",
      "source_ref": "mail_gold_v2_475_scn_2025",
      "title": "科勒展会翻译",
      "reasons": [
        "cleaned_content_too_short"
      ]
    },
    {
      "rank": 476,
      "fragment_id": "3d2333f5-8c7b-479d-b7f6-1c73094df62b",
      "source_ref": "mail_gold_v2_476_scn_2025",
      "title": "与您分享可参考的综合服务场景",
      "reasons": [
        "cleaned_content_too_short"
      ]
    },
    {
      "rank": 477,
      "fragment_id": "5e2a79de-720e-423f-be44-c5a6dcbf040f",
      "source_ref": "mail_gold_v2_477_scn_2025",
      "title": "与您分享可参考的综合服务场景",
      "reasons": [
        "cleaned_content_too_short"
      ]
    },
    {
      "rank": 491,
      "fragment_id": "21a5033f-2028-4872-b570-e2ce180108ad",
      "source_ref": "mail_gold_v2_491_scn_2025",
      "title": "电话没有联系上您，我是SpeedAsia市场部的[发件人],关于视频制作招投标项目与您确认下",
      "reasons": [
        "cleaned_content_too_short"
      ]
    },
    {
      "rank": 494,
      "fragment_id": "a96036a5-a830-4653-88f4-dda4e8d9fff3",
      "source_ref": "mail_gold_v2_494_scn_2024",
      "title": "某化工客户---SpeedAsia合作",
      "reasons": [
        "cleaned_content_too_short"
      ]
    }
  ]
}